bmdOilPriceFetch/__init__.py
bmdOilPriceFetch/bmdOilPriceFetch.py
bmdOilPriceFetch-0.6.2.data/scripts/test.py
bmdOilPriceFetch-0.6.2.dist-info/LICENSE
bmdOilPriceFetch-0.6.2.dist-info/METADATA
bmdOilPriceFetch-0.6.2.dist-info/WHEEL
bmdOilPriceFetch-0.6.2.dist-info/top_level.txt
bmdOilPriceFetch-0.6.2.dist-info/RECORD
